{
  "kitab": {
    "judul": "Ayub 40:1-24",
    "nama": "Ayub",
    "no_kitab": "18",
    "pasal": "40",
    "judul_pasal": "Ayub merendahkan diri di hadapan Allah",
    "ayat_ayat": [
      {
        "ayat": "1",
        "isi": "(39-34) Maka jawab TUHAN kepada Ayub:"
      },
      {
        "ayat": "2",
        "isi": "(39-35) \"Apakah si pengecam hendak berbantah dengan Yang Mahakuasa? Hendaklah yang mencela Allah menjawab!\""
      },
      {
        "ayat": "3",
        "isi": "(39-36) Maka jawab Ayub kepada TUHAN:"
      },
      {
        "ayat": "4",
        "isi": "(39-37) \"Sesungguhnya, aku ini terlalu hina; jawab apakah yang dapat kuberikan kepada-Mu? Mulutku kututup dengan tangan."
      },
      {
        "ayat": "5",
        "isi": "(39-38) Satu kali aku berbicara, tetapi tidak akan kuulangi; bahkan dua kali, tetapi tidak akan kulanjutkan.\""
      },
      {
        "ayat": "6",
        "isi": "(40-1) Maka dari dalam badai TUHAN menjawab Ayub:"
      },
      {
        "ayat": "7",
        "isi": "(40-2) \"Bersiaplah engkau sebagai laki-laki; Aku akan menanyai engkau, dan engkau memberitahu Aku."
      },
      {
        "ayat": "8",
        "isi": "(40-3) Apakah engkau hendak meniadakan pengadilan-Ku, mempersalahkan Aku supaya engkau dapat membenarkan dirimu?"
      },
      {
        "ayat": "9",
        "isi": "(40-4) Apakah lenganmu seperti lengan Allah, dan dapatkah engkau mengguntur seperti Dia?"
      },
      {
        "ayat": "10",
        "isi": "(40-5) Hiasilah dirimu dengan kemegahan dan keluhuran, kenakanlah keagungan dan semarak!"
      },
      {
        "ayat": "11",
        "isi": "(40-6) Luapkanlah marahmu yang bergelora; amat-amatilah setiap orang yang congkak dan rendahkanlah dia!"
      },
      {
        "ayat": "12",
        "isi": "(40-7) Amat-amatilah setiap orang yang congkak, tundukkanlah dia, dan hancurkanlah orang-orang fasik di tempatnya!"
      },
      {
        "ayat": "13",
        "isi": "(40-8) Pendamlah mereka bersama-sama dalam debu, kurunglah mereka di tempat yang tersembunyi."
      },
      {
        "ayat": "14",
        "isi": "(40-9) Maka Akupun akan memuji engkau, karena tangan kananmu memberi engkau kemenangan.\""
      },
      {
        "ayat": "15",
        "isi": "(40-10) \"Perhatikanlah kuda Nil, yang telah Kubuat seperti juga engkau. Ia makan rumput seperti lembu."
      },
      {
        "ayat": "16",
        "isi": "(40-11) Perhatikanlah tenaga di pinggangnya, kekuatan pada urat-urat perutnya!"
      },
      {
        "ayat": "17",
        "isi": "(40-12) Ia meregangkan ekornya seperti pohon aras, otot-otot pahanya berjalin-jalinan."
      },
      {
        "ayat": "18",
        "isi": "(40-13) Tulang-tulangnya seperti pembuluh tembaga, kerangkanya seperti batang besi."
      },
      {
        "ayat": "19",
        "isi": "(40-14) Dia yang pertama dibuat Allah, makhluk yang diberi-Nya bersenjatakan pedang;"
      },
      {
        "ayat": "20",
        "isi": "(40-15) ya, bukit-bukit mengeluarkan hasil baginya, di mana binatang-binatang liar bermain-main."
      },
      {
        "ayat": "21",
        "isi": "(40-16) Di bawah tumbuhan teratai ia menderum, tersembunyi dalam gelagah dan paya."
      },
      {
        "ayat": "22",
        "isi": "(40-17) Tumbuhan-tumbuhan teratai menaungi dia dengan bayang-bayangnya, pohon-pohon gandarusa mengelilinginya."
      },
      {
        "ayat": "23",
        "isi": "(40-18) Sesungguhnya, biarpun sungai sangat kuat arusnya, ia tidak gentar; ia tetap tenang, biarpun sungai Yordan meluap melanda mulutnya."
      },
      {
        "ayat": "24",
        "isi": "(40-19) Dapatkah orang menangkap dia dari muka, mencocok hidungnya dengan keluan?\""
      }
    ]
  }
}