{
  "kitab": {
    "judul": "Mazmur 2:1-12",
    "nama": "Mazmur",
    "no_kitab": "19",
    "pasal": "2",
    "judul_pasal": "Raja yang diurapi TUHAN",
    "ayat_ayat": [
      {
        "ayat": "1",
        "isi": "Mengapa rusuh bangsa-bangsa, mengapa suku-suku bangsa mereka-reka perkara yang sia-sia?"
      },
      {
        "ayat": "2",
        "isi": "Raja-raja dunia bersiap-siap dan para pembesar bermufakat bersama-sama melawan TUHAN dan yang diurapi-Nya:"
      },
      {
        "ayat": "3",
        "isi": "\"Marilah kita memutuskan belenggu-belenggu mereka dan membuang tali-tali mereka dari pada kita!\""
      },
      {
        "ayat": "4",
        "isi": "Dia, yang bersemayam di sorga, tertawa; Tuhan mengolok-olok mereka."
      },
      {
        "ayat": "5",
        "isi": "Maka berkatalah Ia kepada mereka dalam murka-Nya dan mengejutkan mereka dalam kehangatan amarah-Nya:"
      },
      {
        "ayat": "6",
        "isi": "\"Akulah yang telah melantik raja-Ku di Sion, gunung-Ku yang kudus!\""
      },
      {
        "ayat": "7",
        "isi": "Aku mau menceritakan tentang ketetapan TUHAN; Ia berkata kepadaku: \"Anak-Ku engkau! Engkau telah Kuperanakkan pada hari ini."
      },
      {
        "ayat": "8",
        "isi": "Mintalah kepada-Ku, maka bangsa-bangsa akan Kuberikan kepadamu menjadi milik pusakamu, dan ujung bumi menjadi kepunyaanmu."
      },
      {
        "ayat": "9",
        "isi": "Engkau akan meremukkan mereka dengan gada besi, memecahkan mereka seperti tembikar tukang periuk.\""
      },
      {
        "ayat": "10",
        "isi": "Oleh sebab itu, hai raja-raja, bertindaklah bijaksana, terimalah pengajaran, hai para hakim dunia!"
      },
      {
        "ayat": "11",
        "isi": "Beribadahlah kepada TUHAN dengan takut dan ciumlah kaki-Nya dengan gemetar,"
      },
      {
        "ayat": "12",
        "isi": "supaya Ia jangan murka dan kamu binasa di jalan, sebab mudah sekali murka-Nya menyala. Berbahagialah semua orang yang berlindung pada-Nya!"
      }
    ]
  }
}