{
  "kitab": {
    "judul": "Mazmur 6:1-10",
    "nama": "Mazmur",
    "no_kitab": "19",
    "pasal": "6",
    "judul_pasal": "Doa dalam pergumulan",
    "ayat_ayat": [
      {
        "ayat": "1",
        "isi": "Untuk pemimpin biduan. Dengan permainan kecapi. Menurut lagu: Yang kedelapan. Mazmur Daud. (6-2) Ya TUHAN, janganlah menghukum aku dalam murka-Mu, dan janganlah menghajar aku dalam kepanasan amarah-Mu."
      },
      {
        "ayat": "2",
        "isi": "(6-3) Kasihanilah aku, TUHAN, sebab aku merana; sembuhkanlah aku, TUHAN, sebab tulang-tulangku gemetar,"
      },
      {
        "ayat": "3",
        "isi": "(6-4) dan jiwakupun sangat terkejut; tetapi Engkau, TUHAN, berapa lama lagi?"
      },
      {
        "ayat": "4",
        "isi": "(6-5) Kembalilah pula, TUHAN, luputkanlah jiwaku, selamatkanlah aku oleh karena kasih setia-Mu."
      },
      {
        "ayat": "5",
        "isi": "(6-6) Sebab di dalam maut tidaklah orang ingat kepada-Mu; siapakah yang akan bersyukur kepada-Mu di dalam dunia orang mati?"
      },
      {
        "ayat": "6",
        "isi": "(6-7) Lesu aku karena mengeluh; setiap malam aku menggenangi tempat tidurku, dengan air mataku aku membanjiri ranjangku."
      },
      {
        "ayat": "7",
        "isi": "(6-8) Mataku mengidap karena sakit hati, rabun karena semua lawanku."
      },
      {
        "ayat": "8",
        "isi": "(6-9) Menjauhlah dari padaku, kamu sekalian yang melakukan kejahatan, sebab TUHAN telah mendengar tangisku;"
      },
      {
        "ayat": "9",
        "isi": "(6-10) TUHAN telah mendengar permohonanku, TUHAN menerima doaku."
      },
      {
        "ayat": "10",
        "isi": "(6-11) Semua musuhku mendapat malu dan sangat terkejut; mereka mundur dan mendapat malu dalam sekejap mata."
      }
    ]
  }
}