{
  "kitab": {
    "judul": "Mazmur 70:1-5",
    "nama": "Mazmur",
    "no_kitab": "19",
    "pasal": "70",
    "judul_pasal": "Doa minta pertolongan",
    "ayat_ayat": [
      {
        "ayat": "1",
        "isi": "Untuk pemimpin biduan. Dari Daud, pada waktu mempersembahkan korban peringatan. (70-2) Ya Allah, bersegeralah melepaskan aku, menolong aku, ya TUHAN!"
      },
      {
        "ayat": "2",
        "isi": "(70-3) Biarlah mendapat malu dan tersipu-sipu mereka yang ingin mencabut nyawaku; biarlah mundur dan kena noda mereka yang mengingini kecelakaanku;"
      },
      {
        "ayat": "3",
        "isi": "(70-4) biarlah berbalik karena malu mereka yang mengatakan: \"Syukur, syukur!\""
      },
      {
        "ayat": "4",
        "isi": "(70-5) Biarlah bergirang dan bersukacita karena Engkau semua orang yang mencari Engkau; biarlah mereka yang mencintai keselamatan dari pada-Mu selalu berkata: \"Allah itu besar!\""
      },
      {
        "ayat": "5",
        "isi": "(70-6) Tetapi aku ini sengsara dan miskin--ya Allah, segeralah datang! Engkaulah yang menolong aku dan meluputkan aku; ya TUHAN, janganlah lambat datang!"
      }
    ]
  }
}